correspondant/__init__.py
correspondant/__version__.py
correspondant-0.0.1.dist-info/LICENSE
correspondant-0.0.1.dist-info/METADATA
correspondant-0.0.1.dist-info/WHEEL
correspondant-0.0.1.dist-info/top_level.txt
correspondant-0.0.1.dist-info/RECORD
