Metadata-Version: 2.1
Name: correspondant
Version: 0.0.1
Summary: A modular data stream retriever
Home-page: https://pypi.org/project/correspondant
Author: Adam Aquesbi
Author-email: adam.aquesbi@outlook.com
License: UNKNOWN
Platform: UNKNOWN
